passagemath_standard/__init__.py
passagemath_standard-10.6.43.dist-info/licenses/LICENSE.txt
passagemath_standard-10.6.43.dist-info/METADATA
passagemath_standard-10.6.43.dist-info/WHEEL
passagemath_standard-10.6.43.dist-info/top_level.txt
passagemath_standard-10.6.43.dist-info/RECORD
