Metadata-Version: 2.4
Name: passagemath-standard
Version: 10.6.43
Summary: passagemath: Standard Python Library
Author-email: The Sage Developers <sage-support@googlegroups.com>
Maintainer: Matthias Köppe, passagemath contributors
License-Expression: GPL-2.0-or-later
Project-URL: release notes, https://github.com/passagemath/passagemath/releases
Project-URL: repo (upstream), https://github.com/sagemath/sage
Project-URL: repo, https://github.com/passagemath/passagemath
Project-URL: documentation, https://passagemath.org/docs/latest
Project-URL: homepage (upstream), https://www.sagemath.org
Project-URL: discourse, https://passagemath.discourse.group
Project-URL: tracker (upstream), https://github.com/sagemath/sage/issues
Project-URL: tracker, https://github.com/passagemath/passagemath/issues
Classifier: Development Status :: 6 - Mature
Classifier: Intended Audience :: Education
Classifier: Intended Audience :: Science/Research
Classifier: Operating System :: POSIX
Classifier: Operating System :: POSIX :: Linux
Classifier: Operating System :: MacOS :: MacOS X
Classifier: Programming Language :: Python :: 3 :: Only
Classifier: Programming Language :: Python :: 3.10
Classifier: Programming Language :: Python :: 3.11
Classifier: Programming Language :: Python :: 3.12
Classifier: Programming Language :: Python :: 3.13
Classifier: Programming Language :: Python :: 3.14
Classifier: Programming Language :: Python :: Implementation :: CPython
Classifier: Topic :: Scientific/Engineering :: Mathematics
Requires-Python: <3.15,>=3.10
License-File: LICENSE.txt
Requires-Dist: passagemath-standard-no-symbolics~=10.6.43.0
Requires-Dist: passagemath-symbolics~=10.6.43.0
Provides-Extra: 4ti2
Requires-Dist: passagemath-latte-4ti2; extra == "4ti2"
Provides-Extra: benzene
Requires-Dist: passagemath-benzene; extra == "benzene"
Provides-Extra: bliss
Requires-Dist: passagemath-bliss; extra == "bliss"
Provides-Extra: brial
Requires-Dist: passagemath-brial; extra == "brial"
Provides-Extra: buckygen
Requires-Dist: passagemath-buckygen; extra == "buckygen"
Provides-Extra: cliquer
Requires-Dist: passagemath-cliquer; extra == "cliquer"
Provides-Extra: cmr
Requires-Dist: passagemath-cmr; extra == "cmr"
Provides-Extra: coxeter3
Requires-Dist: passagemath-coxeter3; extra == "coxeter3"
Provides-Extra: cvxopt
Requires-Dist: cvxopt>=1.2.5; extra == "cvxopt"
Provides-Extra: cvxpy
Requires-Dist: cvxpy; extra == "cvxpy"
Provides-Extra: database-cremona-ellcurve
Requires-Dist: passagemath-database-cremona-ellcurve; extra == "database-cremona-ellcurve"
Provides-Extra: database-cunningham
Requires-Dist: passagemath-database-cunningham; extra == "database-cunningham"
Provides-Extra: database-jones-numfield
Requires-Dist: passagemath-database-jones-numfield; extra == "database-jones-numfield"
Provides-Extra: database-kohel
Requires-Dist: passagemath-database-kohel; extra == "database-kohel"
Provides-Extra: database-mutation-class
Requires-Dist: passagemath-database-mutation-class; extra == "database-mutation-class"
Provides-Extra: database-odlyzko-zeta
Requires-Dist: passagemath-database-odlyzko-zeta; extra == "database-odlyzko-zeta"
Provides-Extra: database-polytopes-4d
Requires-Dist: passagemath-database-polytopes-4d; extra == "database-polytopes-4d"
Provides-Extra: database-symbolic-data
Requires-Dist: passagemath-database-symbolic-data; extra == "database-symbolic-data"
Provides-Extra: eclib
Requires-Dist: passagemath-eclib; extra == "eclib"
Provides-Extra: frobby
Requires-Dist: passagemath-frobby; extra == "frobby"
Provides-Extra: gfan
Requires-Dist: passagemath-gfan; extra == "gfan"
Provides-Extra: giac
Requires-Dist: passagemath-giac; extra == "giac"
Provides-Extra: glucose
Requires-Dist: passagemath-glucose; extra == "glucose"
Provides-Extra: igraph
Requires-Dist: igraph; extra == "igraph"
Provides-Extra: jupyterlab
Requires-Dist: jupyterlab; extra == "jupyterlab"
Provides-Extra: kenzo
Requires-Dist: passagemath-kenzo; extra == "kenzo"
Provides-Extra: kissat
Requires-Dist: passagemath-kissat; extra == "kissat"
Provides-Extra: latte
Requires-Dist: passagemath-latte-4ti2; extra == "latte"
Provides-Extra: latte-int
Requires-Dist: passagemath-latte-4ti2; extra == "latte-int"
Provides-Extra: lrslib
Requires-Dist: passagemath-lrslib; extra == "lrslib"
Provides-Extra: macaulay2
Requires-Dist: passagemath-macaulay2; extra == "macaulay2"
Provides-Extra: marimo
Requires-Dist: marimo; extra == "marimo"
Provides-Extra: mcqd
Requires-Dist: passagemath-mcqd; extra == "mcqd"
Provides-Extra: meataxe
Requires-Dist: passagemath-meataxe; extra == "meataxe"
Provides-Extra: msolve
Requires-Dist: passagemath-msolve; extra == "msolve"
Provides-Extra: nauty
Requires-Dist: passagemath-nauty; extra == "nauty"
Provides-Extra: networkx
Requires-Dist: networkx>=2.4; extra == "networkx"
Provides-Extra: normaliz
Requires-Dist: pynormaliz==2.21; extra == "normaliz"
Provides-Extra: notebook
Requires-Dist: notebook>=6.1.1; extra == "notebook"
Provides-Extra: palp
Requires-Dist: passagemath-palp; extra == "palp"
Provides-Extra: planarity
Requires-Dist: passagemath-planarity; extra == "planarity"
Provides-Extra: plantri
Requires-Dist: passagemath-plantri; extra == "plantri"
Provides-Extra: polymake
Requires-Dist: jupymake>=0.9; extra == "polymake"
Provides-Extra: qepcad
Requires-Dist: passagemath-qepcad; extra == "qepcad"
Provides-Extra: r
Requires-Dist: rpy2>=3.3; extra == "r"
Provides-Extra: rankwidth
Requires-Dist: passagemath-rankwidth; extra == "rankwidth"
Provides-Extra: rubiks
Requires-Dist: passagemath-rubiks; extra == "rubiks"
Provides-Extra: rw
Requires-Dist: passagemath-rankwidth; extra == "rw"
Provides-Extra: scip
Requires-Dist: PySCIPOpt; extra == "scip"
Provides-Extra: sirocco
Requires-Dist: passagemath-sirocco; extra == "sirocco"
Provides-Extra: sympow
Requires-Dist: passagemath-sympow; extra == "sympow"
Provides-Extra: tdlib
Requires-Dist: passagemath-tdlib; extra == "tdlib"
Provides-Extra: topcom
Requires-Dist: passagemath-topcom; extra == "topcom"
Dynamic: license-file
